Flask_Plugin-0.1.0.data/data/LICENSE
Flask_Plugin-0.1.0.data/data/readme.md
flask_plugin/__init__.py
flask_plugin/config.py
flask_plugin/manager.py
flask_plugin/plugin.py
flask_plugin/plugin.schema.json
flask_plugin/signals.py
flask_plugin/states.py
flask_plugin/utils.py
Flask_Plugin-0.1.0.dist-info/LICENSE
Flask_Plugin-0.1.0.dist-info/METADATA
Flask_Plugin-0.1.0.dist-info/WHEEL
Flask_Plugin-0.1.0.dist-info/top_level.txt
Flask_Plugin-0.1.0.dist-info/RECORD
