Metadata-Version: 2.1
Name: Flask-Plugin
Version: 0.1.0
Summary: An extension to add support of Plugin in Flask.
Home-page: https://github.com/guiqiqi/flask-plugin
Author: Doge Gui
Author-email: guiqiqi187@gmail.com
License: MIT
Platform: any
Classifier: Environment :: Web Environment
Classifier: Development Status :: 3 - Alpha
Classifier: Intended Audience :: Developers
Classifier: Operating System :: OS Independent
Classifier: License :: OSI Approved :: MIT License
Classifier: Programming Language :: Python
Classifier: Programming Language :: Python :: 3
Classifier: Programming Language :: Python :: 3.7
Classifier: Programming Language :: Python :: 3.8
Classifier: Programming Language :: Python :: 3.9
Classifier: Programming Language :: Python :: 3.10
Classifier: Topic :: Internet :: WWW/HTTP :: Dynamic Content
Classifier: Topic :: Software Development :: Libraries :: Python Modules
Requires-Python: >=3.7
Requires-Dist: flask
Requires-Dist: requests
Requires-Dist: jsonschema
